dxsvelte/__init__.py
dxsvelte/dxsvelte.py
dxsvelte-0.2.0a21.dist-info/METADATA
dxsvelte-0.2.0a21.dist-info/WHEEL
dxsvelte-0.2.0a21.dist-info/RECORD
