Metadata-Version: 2.1
Name: dxsvelte
Version: 0.2.0a21
Summary: Bring the power of Svelte to your Django projects.
Project-URL: Homepage, https://dxsvelte.com/
Project-URL: Bug Tracker, https://github.com/emmyarty/dxsvelte/issues
Author: emmyarty
Classifier: License :: OSI Approved :: MIT License
Classifier: Operating System :: OS Independent
Classifier: Programming Language :: Python :: 3
Requires-Python: >=3.10
Requires-Dist: py-mini-racer>=0.6.0
Requires-Dist: sourcemap>=0.2.1
